dymport/__init__.py
dymport/import_file.py
dymport-0.1.0.dist-info/DESCRIPTION.rst
dymport-0.1.0.dist-info/METADATA
dymport-0.1.0.dist-info/RECORD
dymport-0.1.0.dist-info/WHEEL
dymport-0.1.0.dist-info/metadata.json
dymport-0.1.0.dist-info/top_level.txt
tests/import_file/__init__.py
tests/import_file/file.py
tests/import_file/test_import_file.py
