Metadata-Version: 2.0
Name: dymport
Version: 0.1.0
Summary: Dynamically import (abitrary names from) arbitrary files in Python.
Home-page: https://github.com/ErwinJanssen/dymport.py
Author: Erwin Janssen
Author-email: erwinjanssen@outlook.com
License: MIT
